moztest/__init__.py
moztest/resolve.py
moztest/results.py
moztest/adapters/__init__.py
moztest/adapters/unit.py
moztest/selftest/__init__.py
moztest/selftest/fixtures.py
moztest/selftest/output.py
moztest-1.1.0.dist-info/DESCRIPTION.rst
moztest-1.1.0.dist-info/METADATA
moztest-1.1.0.dist-info/RECORD
moztest-1.1.0.dist-info/WHEEL
moztest-1.1.0.dist-info/metadata.json
moztest-1.1.0.dist-info/top_level.txt
