Metadata-Version: 2.0
Name: moztest
Version: 1.1.0
Summary: Package for storing and outputting Mozilla test results
Home-page: https://wiki.mozilla.org/Auto-tools/Projects/Mozbase
Author: Mozilla Automation and Tools team
Author-email: tools@lists.mozilla.org
License: MPL
Keywords: mozilla
Platform: UNKNOWN
Classifier: Programming Language :: Python :: 2.7
Classifier: Programming Language :: Python :: 3
Classifier: Programming Language :: Python :: 3.5
Classifier: Development Status :: 5 - Production/Stable
Requires-Dist: mozinfo
